smtplibaio/__init__.py
smtplibaio/exceptions.py
smtplibaio/smtp.py
smtplibaio/streams.py
smtplibaio-2.1.2.dist-info/LICENSE.txt
smtplibaio-2.1.2.dist-info/WHEEL
smtplibaio-2.1.2.dist-info/METADATA
smtplibaio-2.1.2.dist-info/RECORD
