Metadata-Version: 2.1
Name: smtplibaio
Version: 2.1.2
Summary: An async version of smtplib
Home-page: https://github.com/hwmrocker/smtplibaio
License: MIT
Author: Olaf Gladis
Author-email: github@gladis.org
Requires-Python: >=3.5,<4.0
Classifier: License :: OSI Approved :: MIT License
Classifier: Programming Language :: Python :: 3
Classifier: Programming Language :: Python :: 3.5
Classifier: Programming Language :: Python :: 3.6
Classifier: Programming Language :: Python :: 3.7
Project-URL: Repository, https://github.com/hwmrocker/smtplibaio
